cli.py
rcode_cli-1.0.1.dist-info/licenses/LICENSE
src/__init__.py
src/main.py
src/agents/__init__.py
src/agents/rcode_agent.py
src/checkpoint/__init__.py
src/checkpoint/checkpoint_manager.py
src/commands/__init__.py
src/commands/slash_commands.py
src/config/__init__.py
src/config/config_manager.py
src/context/__init__.py
src/context/code_analyzer.py
src/context/context_provider.py
src/context/context_types.py
src/context/project_context_manager.py
src/context/relationship_mapper.py
src/prompts/__init__.py
src/prompts/system_prompts.py
src/rcode_mcp/__init__.py
src/rcode_mcp/mcp_integration.py
src/tools/__init__.py
src/tools/approval_terminal_operations.py
src/tools/checkpoint_file_operations.py
src/tools/file_operations.py
src/tools/human_approval.py
src/tools/terminal_operations.py
src/tools/web_search.py
src/types/__init__.py
src/types/agent_types.py
src/types/base_types.py
src/types/model_types.py
rcode_cli-1.0.1.dist-info/METADATA
rcode_cli-1.0.1.dist-info/WHEEL
rcode_cli-1.0.1.dist-info/entry_points.txt
rcode_cli-1.0.1.dist-info/top_level.txt
rcode_cli-1.0.1.dist-info/RECORD
