Metadata-Version: 2.4
Name: rcode-cli
Version: 1.0.1
Summary: R-Code AI-Powered Interactive Code Assistant - Advanced CLI tool with intelligent coding assistance
Author-email: Rahees Ahmed <raheesahmed256@gmail.com>
Maintainer-email: Rahees Ahmed <raheesahmed256@gmail.com>
License: GNU AFFERO GENERAL PUBLIC LICENSE
Project-URL: Homepage, https://github.com/RaheesAhmed/R-Code-CLI
Project-URL: Documentation, https://github.com/RaheesAhmed/R-Code-CLI/docs
Project-URL: Repository, https://github.com/RaheesAhmed/R-Code-CLI
Project-URL: Issues, https://github.com/RaheesAhmed/R-Code-CLI/issues
Project-URL: Changelog, https://github.com/RaheesAhmed/R-Code-CLI/releases
Keywords: ai,coding,assistant,cli,development,langchain,langgraph,claude
Classifier: Development Status :: 5 - Production/Stable
Classifier: Environment :: Console
Classifier: Intended Audience :: Developers
Classifier: License :: OSI Approved :: MIT License
Classifier: Operating System :: OS Independent
Classifier: Programming Language :: Python :: 3
Classifier: Programming Language :: Python :: 3.8
Classifier: Programming Language :: Python :: 3.9
Classifier: Programming Language :: Python :: 3.10
Classifier: Programming Language :: Python :: 3.11
Classifier: Programming Language :: Python :: 3.12
Classifier: Topic :: Software Development
Classifier: Topic :: Software Development :: Code Generators
Classifier: Topic :: Software Development :: Debuggers
Classifier: Topic :: System :: Software Distribution
Classifier: Topic :: Utilities
Requires-Python: >=3.8
License-File: LICENSE
Requires-Dist: langchain>=0.3.27
Requires-Dist: langchain-core>=0.3.72
Requires-Dist: langgraph>=0.6.2
Requires-Dist: langchain-anthropic>=0.3.18
Requires-Dist: langchain-openai>=0.3.28
Requires-Dist: langchain-community>=0.3.27
Requires-Dist: langchain-tavily>=0.2.11
Requires-Dist: langchain-text-splitters>=0.3.9
Requires-Dist: langsmith>=0.4.10
Requires-Dist: langchain-mcp-adapters>=0.1.9
Requires-Dist: mcp>=1.12.3
Requires-Dist: rich>=14.1.0
Requires-Dist: python-dotenv>=1.1.0
Requires-Dist: requests>=2.32.0
Requires-Dist: aiohttp>=3.12.0
Requires-Dist: tiktoken>=0.9.0
Requires-Dist: pydantic>=2.11.0
Requires-Dist: pydantic-settings>=2.10.0
Requires-Dist: typing-extensions>=4.14.0
Requires-Dist: dataclasses-json>=0.6.7
Requires-Dist: click>=8.2.0
Requires-Dist: typer>=0.16.0
Requires-Dist: PyYAML>=6.0.0
Requires-Dist: psutil>=7.0.0
Requires-Dist: anthropic>=0.60.0
Requires-Dist: openai>=1.98.0
Requires-Dist: numpy>=2.3.0
Requires-Dist: uvicorn>=0.35.0
Provides-Extra: dev
Requires-Dist: pytest>=7.0.0; extra == "dev"
Requires-Dist: pytest-asyncio>=0.21.0; extra == "dev"
Requires-Dist: black>=23.0.0; extra == "dev"
Requires-Dist: flake8>=6.0.0; extra == "dev"
Requires-Dist: mypy>=1.0.0; extra == "dev"
Requires-Dist: pre-commit>=3.0.0; extra == "dev"
Requires-Dist: twine>=4.0.0; extra == "dev"
Requires-Dist: build>=0.10.0; extra == "dev"
Provides-Extra: docs
Requires-Dist: mkdocs>=1.4.0; extra == "docs"
Requires-Dist: mkdocs-material>=9.0.0; extra == "docs"
Requires-Dist: mkdocstrings>=0.20.0; extra == "docs"
Provides-Extra: all
Requires-Dist: rcode-cli[dev,docs]; extra == "all"
Dynamic: license-file
